venra/__init__.py
venra/__version__.py
venra/client.py
venra/config.py
venra/document.py
venra/exceptions.py
venra/query.py
venra/system.py
venra/visit.py
venra-0.1.6.dist-info/LICENSE
venra-0.1.6.dist-info/METADATA
venra-0.1.6.dist-info/WHEEL
venra-0.1.6.dist-info/top_level.txt
venra-0.1.6.dist-info/RECORD
