Metadata-Version: 2.1
Name: venra
Version: 0.1.6
Summary: Venra provides a simple, high-level api for vespa.ai.
Home-page: https://github.com/codycollier/venra
Author: Cody Collier
Author-email: cody@telnet.org
License: MIT
Keywords: artificial intelligence,information retrieval,machine learning,search
Classifier: Development Status :: 4 - Beta
Classifier: Intended Audience :: Developers
Classifier: Topic :: Scientific/Engineering :: Artificial Intelligence
Classifier: License :: OSI Approved :: MIT License
Classifier: Programming Language :: Python :: 3
Classifier: Programming Language :: Python :: 3.8
Classifier: Programming Language :: Python :: 3.9
Classifier: Programming Language :: Python :: 3.10
Classifier: Programming Language :: Python :: 3.11
Requires-Python: >=3.8, <4
License-File: LICENSE
Requires-Dist: packaging
Requires-Dist: requests
